uio/__init__.py
uio/uio.py
uio-0.2.4.dist-info/entry_points.txt
uio-0.2.4.dist-info/LICENSE
uio-0.2.4.dist-info/WHEEL
uio-0.2.4.dist-info/METADATA
uio-0.2.4.dist-info/RECORD
